AUTHORS.txt
CHANGELOG.rst
LICENSE.txt
README.rst
bbp-workflow-launch.sh
logging.cfg
luigi.cfg
pyproject.toml
requirements.txt
setup.py
bbp_workflow/__init__.py
bbp_workflow/luigi.py
bbp_workflow/settings.py
bbp_workflow/slurm.py
bbp_workflow/target.py
bbp_workflow/task.py
bbp_workflow/util.py
bbp_workflow.egg-info/PKG-INFO
bbp_workflow.egg-info/SOURCES.txt
bbp_workflow.egg-info/dependency_links.txt
bbp_workflow.egg-info/requires.txt
bbp_workflow.egg-info/top_level.txt
bbp_workflow/generation/__init__.py
bbp_workflow/generation/command.py
bbp_workflow/generation/entity.py
bbp_workflow/generation/environment.py
bbp_workflow/generation/exception.py
bbp_workflow/generation/forge_ensure_once.py
bbp_workflow/generation/generator.py
bbp_workflow/generation/generator_base.py
bbp_workflow/generation/parameter.py
bbp_workflow/generation/target.py
bbp_workflow/generation/variant.py
bbp_workflow/generation/workflow.py
bbp_workflow/sbo/__init__.py
bbp_workflow/sbo/target.py
bbp_workflow/sbo/task.py
bbp_workflow/sbo/util.py
bbp_workflow/sbo/analysis/__init__.py
bbp_workflow/sbo/analysis/task.py
bbp_workflow/sbo/analysis/common/__init__.py
bbp_workflow/sbo/analysis/common/task.py
bbp_workflow/sbo/analysis/emodel/__init__.py
bbp_workflow/sbo/analysis/emodel/task.py
bbp_workflow/sbo/analysis/sim/__init__.py
bbp_workflow/sbo/analysis/sim/task.py
bbp_workflow/sbo/circ/__init__.py
bbp_workflow/sbo/circ/task.py
bbp_workflow/sbo/emodel/__init__.py
bbp_workflow/sbo/emodel/task.py
bbp_workflow/sbo/sim/__init__.py
bbp_workflow/sbo/sim/task.py
bbp_workflow/sbo/viz/__init__.py
bbp_workflow/sbo/viz/task.py
bbp_workflow/simulation/__init__.py
bbp_workflow/simulation/sim_writer.py
bbp_workflow/simulation/task.py
bbp_workflow/simulation/util.py
bbp_workflow/simulation/vocab.py
workflows/foo.cfg
workflows/foo.py