Metadata-Version: 2.1
Name: bbp-workflow
Version: 4.1.2
Summary: Automated pipelines of batch jobs using python and the luigi framework
Author: Blue Brain Project, EPFL
License: Apache-2.0
Project-URL: Homepage, https://github.com/BlueBrain/bbp-workflow
Project-URL: Documentation, https://bbp-workflow.readthedocs.io/en/stable/
Project-URL: Repository, https://github.com/BlueBrain/bbp-workflow
Project-URL: Issues, https://github.com/BlueBrain/bbp-workflow/issues
Keywords: computational neuroscience,BlueBrainProject
Classifier: Development Status :: 3 - Alpha
Classifier: Environment :: Console
Classifier: Operating System :: POSIX
Classifier: Topic :: Scientific/Engineering
Classifier: Topic :: Utilities
Requires-Python: >=3.10
License-File: LICENSE.txt
License-File: AUTHORS.txt
Requires-Dist: luigi
Requires-Dist: jsonschema
Requires-Dist: luigi-tools
Requires-Dist: matplotlib
Requires-Dist: bluepysnap
Requires-Dist: voxcell
Requires-Dist: entity-management
Requires-Dist: xarray
Requires-Dist: pint-xarray
Requires-Dist: cheetah3
Requires-Dist: elephant
Requires-Dist: neo
Requires-Dist: pyarrow
Requires-Dist: blue-cwl>=1.0.0
Requires-Dist: brayns
Requires-Dist: pandas
Requires-Dist: bluepyemodel
Requires-Dist: libsonata
Provides-Extra: docs
Requires-Dist: sphinx-bluebrain-theme; extra == "docs"
